strhub/__init__.py
strhub/hubconf.py
strhub/data/__init__.py
strhub/data/aa_overrides.py
strhub/data/augment.py
strhub/data/dataset.py
strhub/data/module.py
strhub/data/utils.py
strhub/models/__init__.py
strhub/models/base.py
strhub/models/modules.py
strhub/models/utils.py
strhub/models/abinet/__init__.py
strhub/models/abinet/attention.py
strhub/models/abinet/backbone.py
strhub/models/abinet/model.py
strhub/models/abinet/model_abinet_iter.py
strhub/models/abinet/model_alignment.py
strhub/models/abinet/model_language.py
strhub/models/abinet/model_vision.py
strhub/models/abinet/resnet.py
strhub/models/abinet/system.py
strhub/models/abinet/transformer.py
strhub/models/crnn/__init__.py
strhub/models/crnn/model.py
strhub/models/crnn/system.py
strhub/models/parseq/__init__.py
strhub/models/parseq/modules.py
strhub/models/parseq/system.py
strhub/models/trba/__init__.py
strhub/models/trba/feature_extraction.py
strhub/models/trba/model.py
strhub/models/trba/prediction.py
strhub/models/trba/system.py
strhub/models/trba/transformation.py
strhub/models/vitstr/__init__.py
strhub/models/vitstr/model.py
strhub/models/vitstr/system.py
ORE_strhub-0.0.1.dist-info/METADATA
ORE_strhub-0.0.1.dist-info/WHEEL
ORE_strhub-0.0.1.dist-info/top_level.txt
ORE_strhub-0.0.1.dist-info/RECORD
